w1thermsensor/__init__.py
w1thermsensor/__main__.py
w1thermsensor/async_core.py
w1thermsensor/calibration_data.py
w1thermsensor/cli.py
w1thermsensor/core.py
w1thermsensor/errors.py
w1thermsensor/kernel.py
w1thermsensor/sensors.py
w1thermsensor/units.py
w1thermsensor-2.2.0.dist-info/LICENSE
w1thermsensor-2.2.0.dist-info/METADATA
w1thermsensor-2.2.0.dist-info/WHEEL
w1thermsensor-2.2.0.dist-info/entry_points.txt
w1thermsensor-2.2.0.dist-info/top_level.txt
w1thermsensor-2.2.0.dist-info/RECORD
