Metadata-Version: 2.1
Name: w1thermsensor
Version: 2.2.0
Summary: A Python package and CLI tool to work with w1 temperature sensors like DS1822, DS18S20 & DS18B20 on the Raspberry Pi, Beagle Bone and other devices.
Home-page: http://github.com/timofurrer/w1thermsensor
Download-URL: http://github.com/timofurrer/w1thermsensor
Author: Timo Furrer
Author-email: tuxtimo@gmail.com
Maintainer: Timo Furrer
Maintainer-email: tuxtimo@gmail.com
License: MIT
Keywords: w1,w1-therm,therm,sensor,raspberry,raspberry pi,gpio,ds
Platform: Linux
Classifier: Development Status :: 5 - Production/Stable
Classifier: Intended Audience :: Developers
Classifier: License :: OSI Approved :: MIT License
Classifier: Natural Language :: English
Classifier: Programming Language :: Python :: 3
Classifier: Programming Language :: Python :: 3.7
Classifier: Programming Language :: Python :: 3.8
Classifier: Programming Language :: Python :: 3.9
Classifier: Programming Language :: Python :: 3.10
Classifier: Programming Language :: Python :: 3.11
Classifier: Programming Language :: Python :: Implementation
Classifier: Programming Language :: Python :: Implementation :: CPython
Classifier: Topic :: Software Development :: Libraries :: Python Modules
Requires-Python: >=3.7
License-File: LICENSE
Requires-Dist: click
Provides-Extra: async
Requires-Dist: aiofiles ; extra == 'async'
Provides-Extra: dev
Requires-Dist: aiofiles ; extra == 'dev'
Requires-Dist: coverage[toml] >=5.0.2 ; extra == 'dev'
Requires-Dist: pytest >5 ; extra == 'dev'
Requires-Dist: pytest-mock ; extra == 'dev'
Requires-Dist: pytest-asyncio ; extra == 'dev'
Requires-Dist: flake8 ; extra == 'dev'
Requires-Dist: black ; extra == 'dev'
Requires-Dist: check-manifest ; extra == 'dev'
Requires-Dist: towncrier ; extra == 'dev'
Provides-Extra: tests
Requires-Dist: aiofiles ; extra == 'tests'
Requires-Dist: coverage[toml] >=5.0.2 ; extra == 'tests'
Requires-Dist: pytest >5 ; extra == 'tests'
Requires-Dist: pytest-mock ; extra == 'tests'
Requires-Dist: pytest-asyncio ; extra == 'tests'
